{
  "color": "#f8f8f8",
  "description": "An open-source, lightning-fast, and hyper-relevant search engine that fits effortlessly into your apps, websites, and workflow.",
  "icon": "@custom:custom:meilisearch-icon",
  "iconColor": "#ff5caa",
  "image": "https://res.cloudinary.com/practicaldev/image/fetch/s--mekYcjRB--/c_limit%2Cf_auto%2Cfl_progressive%2Cq_auto%2Cw_880/https://dev-to-uploads.s3.amazonaws.com/uploads/articles/n9lo10cdv23exdhodgv9.png",
  "list": [
    "Lightning fast",
    "Plug ‘n play",
    "Flexible",
    "Typo tolerant"
  ],
  "name": "Meilisearch",
  "plans": {
    "basic": {
      "currency": "USD",
      "interval": "month",
      "name": "Basic",
      "price": 31
    }
  },
  "subheading": "Search",
  "url": "https://www.meilisearch.com/"
}
